obsinthe/alerts/__init__.py
obsinthe/alerts/grouping.py
obsinthe/deps.py
obsinthe/openshift/symptoms.py
obsinthe/prometheus/__init__.py
obsinthe/prometheus/client.py
obsinthe/prometheus/data.py
obsinthe/prometheus/loader.py
obsinthe/testing/prometheus/__init__.py
obsinthe/testing/prometheus/alerts.py
obsinthe/testing/prometheus/builder.py
obsinthe/testing/prometheus/client.py
obsinthe/utils/data.py
obsinthe/utils/jupyter.py
obsinthe/utils/time.py
obsinthe/vis/alerts.py
obsinthe/vis/clustering.py
obsinthe-0.0.3.dist-info/LICENSE
obsinthe-0.0.3.dist-info/METADATA
obsinthe-0.0.3.dist-info/WHEEL
obsinthe-0.0.3.dist-info/RECORD
